genjaxmix/__init__.py
genjaxmix/_dpmm/__init__.py
genjaxmix/_dpmm/dpmm.py
genjaxmix/analytical/__init__.py
genjaxmix/analytical/logpdf.py
genjaxmix/analytical/marginal_likelihood.py
genjaxmix/analytical/posterior.py
genjaxmix/analytical/sufficient_statistics.py
genjaxmix/model/__init__.py
genjaxmix/model/compile.py
genjaxmix/model/dsl.py
genjaxmix/model/model.py
genjaxmix/model/utils.py
genjaxmix/model/viz.py
genjaxmix/query/mle.py
genjaxmix-0.1.0.dist-info/METADATA
genjaxmix-0.1.0.dist-info/WHEEL
genjaxmix-0.1.0.dist-info/licenses/LICENSE
genjaxmix-0.1.0.dist-info/RECORD
