Metadata-Version: 2.4
Name: genjaxmix
Version: 0.1.0
Summary: dpmm in genjax
License-File: LICENSE
Requires-Python: >=3.12.5
Requires-Dist: genjax>=0.9.3
Requires-Dist: graphviz>=0.20.3
Requires-Dist: jaxtyping>=0.2.36
Requires-Dist: plum-dispatch>=2.5.7
Provides-Extra: m1
Requires-Dist: jax-metal>=0.1.1; extra == 'm1'
